gym_contin/__init__.py
gym_contin/envs/__init__.py
gym_contin/envs/contin_env.py
gym_contin-1.5.0.dist-info/LICENSE
gym_contin-1.5.0.dist-info/METADATA
gym_contin-1.5.0.dist-info/WHEEL
gym_contin-1.5.0.dist-info/top_level.txt
gym_contin-1.5.0.dist-info/RECORD
