Metadata-Version: 2.1
Name: gym-contin
Version: 1.5.0
Summary: A OpenAI Gym Env for continuous actions
Home-page: UNKNOWN
Author: Claudia Viaro
License: MIT
Platform: UNKNOWN
Requires-Dist: gym
